CHANGES.txt
CONTRIBUTORS.txt
README.txt
bootstrap.py
buildout.cfg
setup.py
unweb/__init__.py
unweb.recipe.ploneftp.egg-info/PKG-INFO
unweb.recipe.ploneftp.egg-info/SOURCES.txt
unweb.recipe.ploneftp.egg-info/dependency_links.txt
unweb.recipe.ploneftp.egg-info/entry_points.txt
unweb.recipe.ploneftp.egg-info/namespace_packages.txt
unweb.recipe.ploneftp.egg-info/not-zip-safe
unweb.recipe.ploneftp.egg-info/requires.txt
unweb.recipe.ploneftp.egg-info/top_level.txt
unweb/recipe/__init__.py
unweb/recipe/ploneftp/README.txt
unweb/recipe/ploneftp/__init__.py
unweb/recipe/ploneftp/config.py
unweb/recipe/ploneftp/ctl.py
unweb/recipe/ploneftp/zope_ftpd.py
unweb/recipe/ploneftp/tests/__init__.py
unweb/recipe/ploneftp/tests/test_docs.py