Metadata-Version: 1.0
Name: unweb.recipe.ploneftp
Version: 0.1
Summary: Buildout recipe to configure an ftp proxy for Plone sites
Home-page: http://svn.plone.org/svn/collective/unweb.recipe.ploneftp/
Author: unweb.me
Author-email: we@unweb.me
License: ZPL
Keywords: plone zope ftp buildout
Platform: UNKNOWN
Classifier: Framework :: Buildout
Classifier: Intended Audience :: Developers
Classifier: Topic :: Software Development :: Build Tools
Classifier: License :: OSI Approved :: Zope Public License
